ep_bolfi/__init__.py
ep_bolfi/kadi_tools/__init__.py
ep_bolfi/kadi_tools/collect_and_fit_spline_to_parameterization_points.py
ep_bolfi/kadi_tools/combine_measurement_segments.py
ep_bolfi/kadi_tools/convert_csv_to_parquet.py
ep_bolfi/kadi_tools/eis_parameterization.py
ep_bolfi/kadi_tools/eis_preprocessing.py
ep_bolfi/kadi_tools/eis_visualization.py
ep_bolfi/kadi_tools/extract_measurement_protocol.py
ep_bolfi/kadi_tools/extract_ocv_curve.py
ep_bolfi/kadi_tools/extract_overpotential.py
ep_bolfi/kadi_tools/fit_and_plot_ocv.py
ep_bolfi/kadi_tools/fit_exponential_decay.py
ep_bolfi/kadi_tools/gitt_parameterization.py
ep_bolfi/kadi_tools/gitt_preprocessing.py
ep_bolfi/kadi_tools/gitt_visualization.py
ep_bolfi/kadi_tools/plot_measurement.py
ep_bolfi/kadi_tools/read_csv_datasets.py
ep_bolfi/kadi_tools/read_hdf5_datasets.py
ep_bolfi/kadi_tools/read_measurement_from_parquet.py
ep_bolfi/kadi_tools/select_measurement_segments.py
ep_bolfi/kadi_tools/store_measurement_as_parquet.py
ep_bolfi/models/__init__.py
ep_bolfi/models/analytic_impedance.py
ep_bolfi/models/assess_effective_parameters.py
ep_bolfi/models/ecm_time_domain_simulation.py
ep_bolfi/models/electrolyte.py
ep_bolfi/models/equivalent_circuits.py
ep_bolfi/models/solversetup.py
ep_bolfi/models/standard_parameters.py
ep_bolfi/optimization/EP_BOLFI.py
ep_bolfi/optimization/__init__.py
ep_bolfi/utility/__init__.py
ep_bolfi/utility/dataset_formatting.py
ep_bolfi/utility/fitting_functions.py
ep_bolfi/utility/preprocessing.py
ep_bolfi/utility/visualization.py
ep_bolfi-3.0.2.dist-info/METADATA
ep_bolfi-3.0.2.dist-info/WHEEL
ep_bolfi-3.0.2.dist-info/RECORD
