Metadata-Version: 2.4
Name: ep-bolfi
Version: 3.0.2
Summary: EP-BOLFI (Expectation Propagation with Bayesian Optimization for Likelihood-Free Inference) extends the simulator optimizer BOLFI with the data featurization of Expectation Propagation.
Author-email: Yannick Kuhn <yannick.kuhn@dlr.de>
Maintainer-email: Yannick Kuhn <yannick.kuhn@dlr.de>
Classifier: Development Status :: 5 - Production/Stable
Classifier: Intended Audience :: Science/Research
Classifier: License :: Other/Proprietary License
Classifier: Programming Language :: Python :: 3
Classifier: Programming Language :: Python :: 3.8
Classifier: Programming Language :: Python :: 3.9
Classifier: Programming Language :: Python :: 3.10
Classifier: Programming Language :: Python :: 3.11
Classifier: Programming Language :: Python :: 3.12
Classifier: Topic :: Scientific/Engineering :: Information Analysis
Requires-Python: >=3.8
Requires-Dist: elfi
Requires-Dist: h5py
Requires-Dist: kadi-apy
Requires-Dist: matplotlib
Requires-Dist: numpy==1.26.4
Requires-Dist: pyarrow
Requires-Dist: pybamm
Requires-Dist: pyimpspec
Requires-Dist: scikit-learn
Requires-Dist: scipy
Requires-Dist: sympy
Requires-Dist: tabulate
Requires-Dist: wheel
Requires-Dist: xmlhelpy
